LICENSE
MANIFEST.in
README.md
setup.py
lib_python_pro_gs_2.egg-info/PKG-INFO
lib_python_pro_gs_2.egg-info/SOURCES.txt
lib_python_pro_gs_2.egg-info/dependency_links.txt
lib_python_pro_gs_2.egg-info/not-zip-safe
lib_python_pro_gs_2.egg-info/requires.txt
lib_python_pro_gs_2.egg-info/top_level.txt
libpythonpro2/__init__.py
libpythonpro2/github_api.py